{"schema":{"version":{"fullVersion":"1.5.16","major":"1","minor":"5","patch":"16"},"meta":{"flags":["experimentalData"]},"collections":[{"name":"category","label":"Categories","path":"content/categories","fields":[{"type":"number","name":"precedence","label":"Precedence","description":"The priority of the category in the navigation. Lower numbers are higher in the navigation.","required":true,"namespace":["category","precedence"],"searchable":true,"uid":false},{"type":"string","name":"label","label":"Label","description":"The navigation label for the category","required":true,"namespace":["category","label"],"searchable":true,"uid":false},{"type":"string","name":"title","label":"Title","isTitle":true,"required":true,"namespace":["category","title"],"searchable":true,"uid":false},{"type":"string","name":"description","label":"Description","isBody":true,"namespace":["category","description"],"searchable":true,"uid":false}],"ui":{},"namespace":["category"]},{"name":"resource","label":"Resources","path":"content/resources","format":"mdx","templates":[{"name":"link","label":"Link","fields":[{"type":"string","name":"title","label":"Title","isTitle":true,"required":true,"namespace":["resource","link","title"],"searchable":true,"uid":false},{"type":"string","name":"link","label":"Link","required":true,"namespace":["resource","link","link"],"searchable":true,"uid":false},{"type":"boolean","name":"isExternal","label":"External Link","description":"If true, the link will open in a new tab","namespace":["resource","link","isExternal"],"searchable":true,"uid":false},{"label":"Category","name":"category","type":"reference","collections":["category"],"required":true,"namespace":["resource","link","category"],"searchable":true,"uid":false}],"namespace":["resource","link"]},{"name":"article","label":"Article","fields":[{"type":"string","name":"title","label":"Title","isTitle":true,"required":true,"namespace":["resource","article","title"],"searchable":true,"uid":false},{"type":"string","name":"slug","label":"Slug","required":true,"namespace":["resource","article","slug"],"searchable":true,"uid":false},{"type":"rich-text","name":"content","label":"Content","isBody":true,"required":true,"templates":[{"name":"Youtube","label":"Youtube","fields":[{"name":"videoId","label":"Video ID (e.g. LNR1TIxNjvs)","type":"string","namespace":["resource","article","content","Youtube","videoId"]}],"namespace":["resource","article","content","Youtube"]},{"name":"LinkButton","label":"Link Button","fields":[{"name":"link","label":"Link","type":"string","namespace":["resource","article","content","LinkButton","link"]},{"name":"label","label":"Label","type":"string","namespace":["resource","article","content","LinkButton","label"]}],"namespace":["resource","article","content","LinkButton"]}],"namespace":["resource","article","content"],"searchable":true,"parser":{"type":"mdx"},"uid":false},{"label":"Category","name":"category","type":"reference","collections":["category"],"required":true,"namespace":["resource","article","category"],"searchable":true,"uid":false}],"namespace":["resource","article"]}],"namespace":["resource"]},{"name":"timeline","label":"Timeline","path":"content/timeline","format":"mdx","fields":[{"type":"datetime","name":"timestamp","label":"Timestamp","required":true,"ui":{"timeFormat":"HH:mm"},"namespace":["timeline","timestamp"],"searchable":true,"uid":false},{"type":"string","name":"title","label":"Title","isTitle":true,"required":true,"namespace":["timeline","title"],"searchable":true,"uid":false},{"type":"rich-text","name":"content","label":"Content","isBody":true,"templates":[{"name":"Youtube","label":"Youtube","fields":[{"name":"videoId","label":"Video ID (e.g. LNR1TIxNjvs)","type":"string","namespace":["timeline","content","Youtube","videoId"],"searchable":true,"uid":false}],"namespace":["timeline","content","Youtube"]},{"name":"LinkButton","label":"Link Button","fields":[{"name":"link","label":"Link","type":"string","namespace":["timeline","content","LinkButton","link"],"searchable":true,"uid":false},{"name":"label","label":"Label","type":"string","namespace":["timeline","content","LinkButton","label"],"searchable":true,"uid":false}],"namespace":["timeline","content","LinkButton"]}],"namespace":["timeline","content"],"searchable":true,"parser":{"type":"mdx"},"uid":false}],"ui":{},"namespace":["timeline"]}],"config":{"media":{"tina":{"publicFolder":"public","mediaRoot":""}}}},"lookup":{"DocumentConnection":{"type":"DocumentConnection","resolveType":"multiCollectionDocumentList","collections":["category","resource","timeline"]},"Node":{"type":"Node","resolveType":"nodeDocument"},"DocumentNode":{"type":"DocumentNode","resolveType":"multiCollectionDocument","createDocument":"create","updateDocument":"update"},"Category":{"type":"Category","resolveType":"collectionDocument","collection":"category","createCategory":"create","updateCategory":"update"},"CategoryConnection":{"type":"CategoryConnection","resolveType":"collectionDocumentList","collection":"category"},"ResourceLinkCategory":{"type":"ResourceLinkCategory","resolveType":"multiCollectionDocument","createDocument":"create","updateDocument":"update"},"ResourceArticleCategory":{"type":"ResourceArticleCategory","resolveType":"multiCollectionDocument","createDocument":"create","updateDocument":"update"},"Resource":{"type":"Resource","resolveType":"unionData","collection":"resource","typeMap":{"link":"ResourceLink","article":"ResourceArticle"}},"ResourceConnection":{"type":"ResourceConnection","resolveType":"collectionDocumentList","collection":"resource"},"Timeline":{"type":"Timeline","resolveType":"collectionDocument","collection":"timeline","createTimeline":"create","updateTimeline":"update"},"TimelineConnection":{"type":"TimelineConnection","resolveType":"collectionDocumentList","collection":"timeline"}},"graphql":{"kind":"Document","definitions":[{"kind":"ScalarTypeDefinition","name":{"kind":"Name","value":"Reference"},"description":{"kind":"StringValue","value":"References another document, used as a foreign key"},"directives":[]},{"kind":"ScalarTypeDefinition","name":{"kind":"Name","value":"JSON"},"description":{"kind":"StringValue","value":""},"directives":[]},{"kind":"ObjectTypeDefinition","interfaces":[],"directives":[],"name":{"kind":"Name","value":"SystemInfo"},"fields":[{"kind":"FieldDefinition","name":{"kind":"Name","value":"filename"},"arguments":[],"type":{"kind":"NonNullType","type":{"kind":"NamedType","name":{"kind":"Name","value":"String"}}}},{"kind":"FieldDefinition","name":{"kind":"Name","value":"title"},"arguments":[],"type":{"kind":"NamedType","name":{"kind":"Name","value":"String"}}},{"kind":"FieldDefinition","name":{"kind":"Name","value":"basename"},"arguments":[],"type":{"kind":"NonNullType","type":{"kind":"NamedType","name":{"kind":"Name","value":"String"}}}},{"kind":"FieldDefinition","name":{"kind":"Name","value":"hasReferences"},"arguments":[],"type":{"kind":"NamedType","name":{"kind":"Name","value":"Boolean"}}},{"kind":"FieldDefinition","name":{"kind":"Name","value":"breadcrumbs"},"arguments":[{"kind":"InputValueDefinition","name":{"kind":"Name","value":"excludeExtension"},"type":{"kind":"NamedType","name":{"kind":"Name","value":"Boolean"}}}],"type":{"kind":"NonNullType","type":{"kind":"ListType","type":{"kind":"NonNullType","type":{"kind":"NamedType","name":{"kind":"Name","value":"String"}}}}}},{"kind":"FieldDefinition","name":{"kind":"Name","value":"path"},"arguments":[],"type":{"kind":"NonNullType","type":{"kind":"NamedType","name":{"kind":"Name","value":"String"}}}},{"kind":"FieldDefinition","name":{"kind":"Name","value":"relativePath"},"arguments":[],"type":{"kind":"NonNullType","type":{"kind":"NamedType","name":{"kind":"Name","value":"String"}}}},{"kind":"FieldDefinition","name":{"kind":"Name","value":"extension"},"arguments":[],"type":{"kind":"NonNullType","type":{"kind":"NamedType","name":{"kind":"Name","value":"String"}}}},{"kind":"FieldDefinition","name":{"kind":"Name","value":"template"},"arguments":[],"type":{"kind":"NonNullType","type":{"kind":"NamedType","name":{"kind":"Name","value":"String"}}}},{"kind":"FieldDefinition","name":{"kind":"Name","value":"collection"},"arguments":[],"type":{"kind":"NonNullType","type":{"kind":"NamedType","name":{"kind":"Name","value":"Collection"}}}}]},{"kind":"ObjectTypeDefinition","interfaces":[],"directives":[],"name":{"kind":"Name","value":"Folder"},"fields":[{"kind":"FieldDefinition","name":{"kind":"Name","value":"name"},"arguments":[],"type":{"kind":"NonNullType","type":{"kind":"NamedType","name":{"kind":"Name","value":"String"}}}},{"kind":"FieldDefinition","name":{"kind":"Name","value":"path"},"arguments":[],"type":{"kind":"NonNullType","type":{"kind":"NamedType","name":{"kind":"Name","value":"String"}}}}]},{"kind":"ObjectTypeDefinition","interfaces":[],"directives":[],"name":{"kind":"Name","value":"PageInfo"},"fields":[{"kind":"FieldDefinition","name":{"kind":"Name","value":"hasPreviousPage"},"arguments":[],"type":{"kind":"NonNullType","type":{"kind":"NamedType","name":{"kind":"Name","value":"Boolean"}}}},{"kind":"FieldDefinition","name":{"kind":"Name","value":"hasNextPage"},"arguments":[],"type":{"kind":"NonNullType","type":{"kind":"NamedType","name":{"kind":"Name","value":"Boolean"}}}},{"kind":"FieldDefinition","name":{"kind":"Name","value":"startCursor"},"arguments":[],"type":{"kind":"NonNullType","type":{"kind":"NamedType","name":{"kind":"Name","value":"String"}}}},{"kind":"FieldDefinition","name":{"kind":"Name","value":"endCursor"},"arguments":[],"type":{"kind":"NonNullType","type":{"kind":"NamedType","name":{"kind":"Name","value":"String"}}}}]},{"kind":"InterfaceTypeDefinition","description":{"kind":"StringValue","value":""},"name":{"kind":"Name","value":"Node"},"interfaces":[],"directives":[],"fields":[{"kind":"FieldDefinition","name":{"kind":"Name","value":"id"},"arguments":[],"type":{"kind":"NonNullType","type":{"kind":"NamedType","name":{"kind":"Name","value":"ID"}}}}]},{"kind":"InterfaceTypeDefinition","description":{"kind":"StringValue","value":""},"name":{"kind":"Name","value":"Document"},"interfaces":[],"directives":[],"fields":[{"kind":"FieldDefinition","name":{"kind":"Name","value":"id"},"arguments":[],"type":{"kind":"NonNullType","type":{"kind":"NamedType","name":{"kind":"Name","value":"ID"}}}},{"kind":"FieldDefinition","name":{"kind":"Name","value":"_sys"},"arguments":[],"type":{"kind":"NamedType","name":{"kind":"Name","value":"SystemInfo"}}},{"kind":"FieldDefinition","name":{"kind":"Name","value":"_values"},"arguments":[],"type":{"kind":"NonNullType","type":{"kind":"NamedType","name":{"kind":"Name","value":"JSON"}}}}]},{"kind":"InterfaceTypeDefinition","description":{"kind":"StringValue","value":"A relay-compliant pagination connection"},"name":{"kind":"Name","value":"Connection"},"interfaces":[],"directives":[],"fields":[{"kind":"FieldDefinition","name":{"kind":"Name","value":"totalCount"},"arguments":[],"type":{"kind":"NonNullType","type":{"kind":"NamedType","name":{"kind":"Name","value":"Float"}}}},{"kind":"FieldDefinition","name":{"kind":"Name","value":"pageInfo"},"arguments":[],"type":{"kind":"NonNullType","type":{"kind":"NamedType","name":{"kind":"Name","value":"PageInfo"}}}}]},{"kind":"ObjectTypeDefinition","interfaces":[],"directives":[],"name":{"kind":"Name","value":"Query"},"fields":[{"kind":"FieldDefinition","name":{"kind":"Name","value":"getOptimizedQuery"},"arguments":[{"kind":"InputValueDefinition","name":{"kind":"Name","value":"queryString"},"type":{"kind":"NonNullType","type":{"kind":"NamedType","name":{"kind":"Name","value":"String"}}}}],"type":{"kind":"NamedType","name":{"kind":"Name","value":"String"}}},{"kind":"FieldDefinition","name":{"kind":"Name","value":"collection"},"arguments":[{"kind":"InputValueDefinition","name":{"kind":"Name","value":"collection"},"type":{"kind":"NamedType","name":{"kind":"Name","value":"String"}}}],"type":{"kind":"NonNullType","type":{"kind":"NamedType","name":{"kind":"Name","value":"Collection"}}}},{"kind":"FieldDefinition","name":{"kind":"Name","value":"collections"},"arguments":[],"type":{"kind":"NonNullType","type":{"kind":"ListType","type":{"kind":"NonNullType","type":{"kind":"NamedType","name":{"kind":"Name","value":"Collection"}}}}}},{"kind":"FieldDefinition","name":{"kind":"Name","value":"node"},"arguments":[{"kind":"InputValueDefinition","name":{"kind":"Name","value":"id"},"type":{"kind":"NamedType","name":{"kind":"Name","value":"String"}}}],"type":{"kind":"NonNullType","type":{"kind":"NamedType","name":{"kind":"Name","value":"Node"}}}},{"kind":"FieldDefinition","name":{"kind":"Name","value":"document"},"arguments":[{"kind":"InputValueDefinition","name":{"kind":"Name","value":"collection"},"type":{"kind":"NamedType","name":{"kind":"Name","value":"String"}}},{"kind":"InputValueDefinition","name":{"kind":"Name","value":"relativePath"},"type":{"kind":"NamedType","name":{"kind":"Name","value":"String"}}}],"type":{"kind":"NonNullType","type":{"kind":"NamedType","name":{"kind":"Name","value":"DocumentNode"}}}},{"kind":"FieldDefinition","name":{"kind":"Name","value":"category"},"arguments":[{"kind":"InputValueDefinition","name":{"kind":"Name","value":"relativePath"},"type":{"kind":"NamedType","name":{"kind":"Name","value":"String"}}}],"type":{"kind":"NonNullType","type":{"kind":"NamedType","name":{"kind":"Name","value":"Category"}}}},{"kind":"FieldDefinition","name":{"kind":"Name","value":"categoryConnection"},"arguments":[{"kind":"InputValueDefinition","name":{"kind":"Name","value":"before"},"type":{"kind":"NamedType","name":{"kind":"Name","value":"String"}}},{"kind":"InputValueDefinition","name":{"kind":"Name","value":"after"},"type":{"kind":"NamedType","name":{"kind":"Name","value":"String"}}},{"kind":"InputValueDefinition","name":{"kind":"Name","value":"first"},"type":{"kind":"NamedType","name":{"kind":"Name","value":"Float"}}},{"kind":"InputValueDefinition","name":{"kind":"Name","value":"last"},"type":{"kind":"NamedType","name":{"kind":"Name","value":"Float"}}},{"kind":"InputValueDefinition","name":{"kind":"Name","value":"sort"},"type":{"kind":"NamedType","name":{"kind":"Name","value":"String"}}},{"kind":"InputValueDefinition","name":{"kind":"Name","value":"filter"},"type":{"kind":"NamedType","name":{"kind":"Name","value":"CategoryFilter"}}}],"type":{"kind":"NonNullType","type":{"kind":"NamedType","name":{"kind":"Name","value":"CategoryConnection"}}}},{"kind":"FieldDefinition","name":{"kind":"Name","value":"resource"},"arguments":[{"kind":"InputValueDefinition","name":{"kind":"Name","value":"relativePath"},"type":{"kind":"NamedType","name":{"kind":"Name","value":"String"}}}],"type":{"kind":"NonNullType","type":{"kind":"NamedType","name":{"kind":"Name","value":"Resource"}}}},{"kind":"FieldDefinition","name":{"kind":"Name","value":"resourceConnection"},"arguments":[{"kind":"InputValueDefinition","name":{"kind":"Name","value":"before"},"type":{"kind":"NamedType","name":{"kind":"Name","value":"String"}}},{"kind":"InputValueDefinition","name":{"kind":"Name","value":"after"},"type":{"kind":"NamedType","name":{"kind":"Name","value":"String"}}},{"kind":"InputValueDefinition","name":{"kind":"Name","value":"first"},"type":{"kind":"NamedType","name":{"kind":"Name","value":"Float"}}},{"kind":"InputValueDefinition","name":{"kind":"Name","value":"last"},"type":{"kind":"NamedType","name":{"kind":"Name","value":"Float"}}},{"kind":"InputValueDefinition","name":{"kind":"Name","value":"sort"},"type":{"kind":"NamedType","name":{"kind":"Name","value":"String"}}},{"kind":"InputValueDefinition","name":{"kind":"Name","value":"filter"},"type":{"kind":"NamedType","name":{"kind":"Name","value":"ResourceFilter"}}}],"type":{"kind":"NonNullType","type":{"kind":"NamedType","name":{"kind":"Name","value":"ResourceConnection"}}}},{"kind":"FieldDefinition","name":{"kind":"Name","value":"timeline"},"arguments":[{"kind":"InputValueDefinition","name":{"kind":"Name","value":"relativePath"},"type":{"kind":"NamedType","name":{"kind":"Name","value":"String"}}}],"type":{"kind":"NonNullType","type":{"kind":"NamedType","name":{"kind":"Name","value":"Timeline"}}}},{"kind":"FieldDefinition","name":{"kind":"Name","value":"timelineConnection"},"arguments":[{"kind":"InputValueDefinition","name":{"kind":"Name","value":"before"},"type":{"kind":"NamedType","name":{"kind":"Name","value":"String"}}},{"kind":"InputValueDefinition","name":{"kind":"Name","value":"after"},"type":{"kind":"NamedType","name":{"kind":"Name","value":"String"}}},{"kind":"InputValueDefinition","name":{"kind":"Name","value":"first"},"type":{"kind":"NamedType","name":{"kind":"Name","value":"Float"}}},{"kind":"InputValueDefinition","name":{"kind":"Name","value":"last"},"type":{"kind":"NamedType","name":{"kind":"Name","value":"Float"}}},{"kind":"InputValueDefinition","name":{"kind":"Name","value":"sort"},"type":{"kind":"NamedType","name":{"kind":"Name","value":"String"}}},{"kind":"InputValueDefinition","name":{"kind":"Name","value":"filter"},"type":{"kind":"NamedType","name":{"kind":"Name","value":"TimelineFilter"}}}],"type":{"kind":"NonNullType","type":{"kind":"NamedType","name":{"kind":"Name","value":"TimelineConnection"}}}}]},{"kind":"InputObjectTypeDefinition","name":{"kind":"Name","value":"DocumentFilter"},"fields":[{"kind":"InputValueDefinition","name":{"kind":"Name","value":"category"},"type":{"kind":"NamedType","name":{"kind":"Name","value":"CategoryFilter"}}},{"kind":"InputValueDefinition","name":{"kind":"Name","value":"resource"},"type":{"kind":"NamedType","name":{"kind":"Name","value":"ResourceFilter"}}},{"kind":"InputValueDefinition","name":{"kind":"Name","value":"timeline"},"type":{"kind":"NamedType","name":{"kind":"Name","value":"TimelineFilter"}}}]},{"kind":"ObjectTypeDefinition","interfaces":[],"directives":[],"name":{"kind":"Name","value":"DocumentConnectionEdges"},"fields":[{"kind":"FieldDefinition","name":{"kind":"Name","value":"cursor"},"arguments":[],"type":{"kind":"NonNullType","type":{"kind":"NamedType","name":{"kind":"Name","value":"String"}}}},{"kind":"FieldDefinition","name":{"kind":"Name","value":"node"},"arguments":[],"type":{"kind":"NamedType","name":{"kind":"Name","value":"DocumentNode"}}}]},{"kind":"ObjectTypeDefinition","interfaces":[{"kind":"NamedType","name":{"kind":"Name","value":"Connection"}}],"directives":[],"name":{"kind":"Name","value":"DocumentConnection"},"fields":[{"kind":"FieldDefinition","name":{"kind":"Name","value":"pageInfo"},"arguments":[],"type":{"kind":"NonNullType","type":{"kind":"NamedType","name":{"kind":"Name","value":"PageInfo"}}}},{"kind":"FieldDefinition","name":{"kind":"Name","value":"totalCount"},"arguments":[],"type":{"kind":"NonNullType","type":{"kind":"NamedType","name":{"kind":"Name","value":"Float"}}}},{"kind":"FieldDefinition","name":{"kind":"Name","value":"edges"},"arguments":[],"type":{"kind":"ListType","type":{"kind":"NamedType","name":{"kind":"Name","value":"DocumentConnectionEdges"}}}}]},{"kind":"ObjectTypeDefinition","interfaces":[],"directives":[],"name":{"kind":"Name","value":"Collection"},"fields":[{"kind":"FieldDefinition","name":{"kind":"Name","value":"name"},"arguments":[],"type":{"kind":"NonNullType","type":{"kind":"NamedType","name":{"kind":"Name","value":"String"}}}},{"kind":"FieldDefinition","name":{"kind":"Name","value":"slug"},"arguments":[],"type":{"kind":"NonNullType","type":{"kind":"NamedType","name":{"kind":"Name","value":"String"}}}},{"kind":"FieldDefinition","name":{"kind":"Name","value":"label"},"arguments":[],"type":{"kind":"NamedType","name":{"kind":"Name","value":"String"}}},{"kind":"FieldDefinition","name":{"kind":"Name","value":"path"},"arguments":[],"type":{"kind":"NonNullType","type":{"kind":"NamedType","name":{"kind":"Name","value":"String"}}}},{"kind":"FieldDefinition","name":{"kind":"Name","value":"format"},"arguments":[],"type":{"kind":"NamedType","name":{"kind":"Name","value":"String"}}},{"kind":"FieldDefinition","name":{"kind":"Name","value":"matches"},"arguments":[],"type":{"kind":"NamedType","name":{"kind":"Name","value":"String"}}},{"kind":"FieldDefinition","name":{"kind":"Name","value":"templates"},"arguments":[],"type":{"kind":"ListType","type":{"kind":"NamedType","name":{"kind":"Name","value":"JSON"}}}},{"kind":"FieldDefinition","name":{"kind":"Name","value":"fields"},"arguments":[],"type":{"kind":"ListType","type":{"kind":"NamedType","name":{"kind":"Name","value":"JSON"}}}},{"kind":"FieldDefinition","name":{"kind":"Name","value":"documents"},"arguments":[{"kind":"InputValueDefinition","name":{"kind":"Name","value":"before"},"type":{"kind":"NamedType","name":{"kind":"Name","value":"String"}}},{"kind":"InputValueDefinition","name":{"kind":"Name","value":"after"},"type":{"kind":"NamedType","name":{"kind":"Name","value":"String"}}},{"kind":"InputValueDefinition","name":{"kind":"Name","value":"first"},"type":{"kind":"NamedType","name":{"kind":"Name","value":"Float"}}},{"kind":"InputValueDefinition","name":{"kind":"Name","value":"last"},"type":{"kind":"NamedType","name":{"kind":"Name","value":"Float"}}},{"kind":"InputValueDefinition","name":{"kind":"Name","value":"sort"},"type":{"kind":"NamedType","name":{"kind":"Name","value":"String"}}},{"kind":"InputValueDefinition","name":{"kind":"Name","value":"filter"},"type":{"kind":"NamedType","name":{"kind":"Name","value":"DocumentFilter"}}},{"kind":"InputValueDefinition","name":{"kind":"Name","value":"folder"},"type":{"kind":"NamedType","name":{"kind":"Name","value":"String"}}}],"type":{"kind":"NonNullType","type":{"kind":"NamedType","name":{"kind":"Name","value":"DocumentConnection"}}}}]},{"kind":"UnionTypeDefinition","name":{"kind":"Name","value":"DocumentNode"},"directives":[],"types":[{"kind":"NamedType","name":{"kind":"Name","value":"Category"}},{"kind":"NamedType","name":{"kind":"Name","value":"ResourceLink"}},{"kind":"NamedType","name":{"kind":"Name","value":"ResourceArticle"}},{"kind":"NamedType","name":{"kind":"Name","value":"Timeline"}},{"kind":"NamedType","name":{"kind":"Name","value":"Folder"}}]},{"kind":"ObjectTypeDefinition","interfaces":[{"kind":"NamedType","name":{"kind":"Name","value":"Node"}},{"kind":"NamedType","name":{"kind":"Name","value":"Document"}}],"directives":[],"name":{"kind":"Name","value":"Category"},"fields":[{"kind":"FieldDefinition","name":{"kind":"Name","value":"precedence"},"arguments":[],"type":{"kind":"NonNullType","type":{"kind":"NamedType","name":{"kind":"Name","value":"Float"}}}},{"kind":"FieldDefinition","name":{"kind":"Name","value":"label"},"arguments":[],"type":{"kind":"NonNullType","type":{"kind":"NamedType","name":{"kind":"Name","value":"String"}}}},{"kind":"FieldDefinition","name":{"kind":"Name","value":"title"},"arguments":[],"type":{"kind":"NonNullType","type":{"kind":"NamedType","name":{"kind":"Name","value":"String"}}}},{"kind":"FieldDefinition","name":{"kind":"Name","value":"description"},"arguments":[],"type":{"kind":"NamedType","name":{"kind":"Name","value":"String"}}},{"kind":"FieldDefinition","name":{"kind":"Name","value":"id"},"arguments":[],"type":{"kind":"NonNullType","type":{"kind":"NamedType","name":{"kind":"Name","value":"ID"}}}},{"kind":"FieldDefinition","name":{"kind":"Name","value":"_sys"},"arguments":[],"type":{"kind":"NonNullType","type":{"kind":"NamedType","name":{"kind":"Name","value":"SystemInfo"}}}},{"kind":"FieldDefinition","name":{"kind":"Name","value":"_values"},"arguments":[],"type":{"kind":"NonNullType","type":{"kind":"NamedType","name":{"kind":"Name","value":"JSON"}}}}]},{"kind":"InputObjectTypeDefinition","name":{"kind":"Name","value":"NumberFilter"},"fields":[{"kind":"InputValueDefinition","name":{"kind":"Name","value":"lt"},"type":{"kind":"NamedType","name":{"kind":"Name","value":"Float"}}},{"kind":"InputValueDefinition","name":{"kind":"Name","value":"lte"},"type":{"kind":"NamedType","name":{"kind":"Name","value":"Float"}}},{"kind":"InputValueDefinition","name":{"kind":"Name","value":"gte"},"type":{"kind":"NamedType","name":{"kind":"Name","value":"Float"}}},{"kind":"InputValueDefinition","name":{"kind":"Name","value":"gt"},"type":{"kind":"NamedType","name":{"kind":"Name","value":"Float"}}},{"kind":"InputValueDefinition","name":{"kind":"Name","value":"eq"},"type":{"kind":"NamedType","name":{"kind":"Name","value":"Float"}}},{"kind":"InputValueDefinition","name":{"kind":"Name","value":"exists"},"type":{"kind":"NamedType","name":{"kind":"Name","value":"Boolean"}}},{"kind":"InputValueDefinition","name":{"kind":"Name","value":"in"},"type":{"kind":"ListType","type":{"kind":"NamedType","name":{"kind":"Name","value":"Float"}}}}]},{"kind":"InputObjectTypeDefinition","name":{"kind":"Name","value":"StringFilter"},"fields":[{"kind":"InputValueDefinition","name":{"kind":"Name","value":"startsWith"},"type":{"kind":"NamedType","name":{"kind":"Name","value":"String"}}},{"kind":"InputValueDefinition","name":{"kind":"Name","value":"eq"},"type":{"kind":"NamedType","name":{"kind":"Name","value":"String"}}},{"kind":"InputValueDefinition","name":{"kind":"Name","value":"exists"},"type":{"kind":"NamedType","name":{"kind":"Name","value":"Boolean"}}},{"kind":"InputValueDefinition","name":{"kind":"Name","value":"in"},"type":{"kind":"ListType","type":{"kind":"NamedType","name":{"kind":"Name","value":"String"}}}}]},{"kind":"InputObjectTypeDefinition","name":{"kind":"Name","value":"CategoryFilter"},"fields":[{"kind":"InputValueDefinition","name":{"kind":"Name","value":"precedence"},"type":{"kind":"NamedType","name":{"kind":"Name","value":"NumberFilter"}}},{"kind":"InputValueDefinition","name":{"kind":"Name","value":"label"},"type":{"kind":"NamedType","name":{"kind":"Name","value":"StringFilter"}}},{"kind":"InputValueDefinition","name":{"kind":"Name","value":"title"},"type":{"kind":"NamedType","name":{"kind":"Name","value":"StringFilter"}}},{"kind":"InputValueDefinition","name":{"kind":"Name","value":"description"},"type":{"kind":"NamedType","name":{"kind":"Name","value":"StringFilter"}}}]},{"kind":"ObjectTypeDefinition","interfaces":[],"directives":[],"name":{"kind":"Name","value":"CategoryConnectionEdges"},"fields":[{"kind":"FieldDefinition","name":{"kind":"Name","value":"cursor"},"arguments":[],"type":{"kind":"NonNullType","type":{"kind":"NamedType","name":{"kind":"Name","value":"String"}}}},{"kind":"FieldDefinition","name":{"kind":"Name","value":"node"},"arguments":[],"type":{"kind":"NamedType","name":{"kind":"Name","value":"Category"}}}]},{"kind":"ObjectTypeDefinition","interfaces":[{"kind":"NamedType","name":{"kind":"Name","value":"Connection"}}],"directives":[],"name":{"kind":"Name","value":"CategoryConnection"},"fields":[{"kind":"FieldDefinition","name":{"kind":"Name","value":"pageInfo"},"arguments":[],"type":{"kind":"NonNullType","type":{"kind":"NamedType","name":{"kind":"Name","value":"PageInfo"}}}},{"kind":"FieldDefinition","name":{"kind":"Name","value":"totalCount"},"arguments":[],"type":{"kind":"NonNullType","type":{"kind":"NamedType","name":{"kind":"Name","value":"Float"}}}},{"kind":"FieldDefinition","name":{"kind":"Name","value":"edges"},"arguments":[],"type":{"kind":"ListType","type":{"kind":"NamedType","name":{"kind":"Name","value":"CategoryConnectionEdges"}}}}]},{"kind":"UnionTypeDefinition","name":{"kind":"Name","value":"ResourceLinkCategory"},"directives":[],"types":[{"kind":"NamedType","name":{"kind":"Name","value":"Category"}}]},{"kind":"ObjectTypeDefinition","interfaces":[{"kind":"NamedType","name":{"kind":"Name","value":"Node"}},{"kind":"NamedType","name":{"kind":"Name","value":"Document"}}],"directives":[],"name":{"kind":"Name","value":"ResourceLink"},"fields":[{"kind":"FieldDefinition","name":{"kind":"Name","value":"title"},"arguments":[],"type":{"kind":"NonNullType","type":{"kind":"NamedType","name":{"kind":"Name","value":"String"}}}},{"kind":"FieldDefinition","name":{"kind":"Name","value":"link"},"arguments":[],"type":{"kind":"NonNullType","type":{"kind":"NamedType","name":{"kind":"Name","value":"String"}}}},{"kind":"FieldDefinition","name":{"kind":"Name","value":"isExternal"},"arguments":[],"type":{"kind":"NamedType","name":{"kind":"Name","value":"Boolean"}}},{"kind":"FieldDefinition","name":{"kind":"Name","value":"category"},"arguments":[],"type":{"kind":"NonNullType","type":{"kind":"NamedType","name":{"kind":"Name","value":"ResourceLinkCategory"}}}},{"kind":"FieldDefinition","name":{"kind":"Name","value":"id"},"arguments":[],"type":{"kind":"NonNullType","type":{"kind":"NamedType","name":{"kind":"Name","value":"ID"}}}},{"kind":"FieldDefinition","name":{"kind":"Name","value":"_sys"},"arguments":[],"type":{"kind":"NonNullType","type":{"kind":"NamedType","name":{"kind":"Name","value":"SystemInfo"}}}},{"kind":"FieldDefinition","name":{"kind":"Name","value":"_values"},"arguments":[],"type":{"kind":"NonNullType","type":{"kind":"NamedType","name":{"kind":"Name","value":"JSON"}}}}]},{"kind":"UnionTypeDefinition","name":{"kind":"Name","value":"ResourceArticleCategory"},"directives":[],"types":[{"kind":"NamedType","name":{"kind":"Name","value":"Category"}}]},{"kind":"ObjectTypeDefinition","interfaces":[{"kind":"NamedType","name":{"kind":"Name","value":"Node"}},{"kind":"NamedType","name":{"kind":"Name","value":"Document"}}],"directives":[],"name":{"kind":"Name","value":"ResourceArticle"},"fields":[{"kind":"FieldDefinition","name":{"kind":"Name","value":"title"},"arguments":[],"type":{"kind":"NonNullType","type":{"kind":"NamedType","name":{"kind":"Name","value":"String"}}}},{"kind":"FieldDefinition","name":{"kind":"Name","value":"slug"},"arguments":[],"type":{"kind":"NonNullType","type":{"kind":"NamedType","name":{"kind":"Name","value":"String"}}}},{"kind":"FieldDefinition","name":{"kind":"Name","value":"content"},"arguments":[],"type":{"kind":"NonNullType","type":{"kind":"NamedType","name":{"kind":"Name","value":"JSON"}}}},{"kind":"FieldDefinition","name":{"kind":"Name","value":"category"},"arguments":[],"type":{"kind":"NonNullType","type":{"kind":"NamedType","name":{"kind":"Name","value":"ResourceArticleCategory"}}}},{"kind":"FieldDefinition","name":{"kind":"Name","value":"id"},"arguments":[],"type":{"kind":"NonNullType","type":{"kind":"NamedType","name":{"kind":"Name","value":"ID"}}}},{"kind":"FieldDefinition","name":{"kind":"Name","value":"_sys"},"arguments":[],"type":{"kind":"NonNullType","type":{"kind":"NamedType","name":{"kind":"Name","value":"SystemInfo"}}}},{"kind":"FieldDefinition","name":{"kind":"Name","value":"_values"},"arguments":[],"type":{"kind":"NonNullType","type":{"kind":"NamedType","name":{"kind":"Name","value":"JSON"}}}}]},{"kind":"UnionTypeDefinition","name":{"kind":"Name","value":"Resource"},"directives":[],"types":[{"kind":"NamedType","name":{"kind":"Name","value":"ResourceLink"}},{"kind":"NamedType","name":{"kind":"Name","value":"ResourceArticle"}}]},{"kind":"InputObjectTypeDefinition","name":{"kind":"Name","value":"BooleanFilter"},"fields":[{"kind":"InputValueDefinition","name":{"kind":"Name","value":"eq"},"type":{"kind":"NamedType","name":{"kind":"Name","value":"Boolean"}}},{"kind":"InputValueDefinition","name":{"kind":"Name","value":"exists"},"type":{"kind":"NamedType","name":{"kind":"Name","value":"Boolean"}}}]},{"kind":"InputObjectTypeDefinition","name":{"kind":"Name","value":"ResourceLinkCategoryFilter"},"fields":[{"kind":"InputValueDefinition","name":{"kind":"Name","value":"category"},"type":{"kind":"NamedType","name":{"kind":"Name","value":"CategoryFilter"}}}]},{"kind":"InputObjectTypeDefinition","name":{"kind":"Name","value":"ResourceLinkFilter"},"fields":[{"kind":"InputValueDefinition","name":{"kind":"Name","value":"title"},"type":{"kind":"NamedType","name":{"kind":"Name","value":"StringFilter"}}},{"kind":"InputValueDefinition","name":{"kind":"Name","value":"link"},"type":{"kind":"NamedType","name":{"kind":"Name","value":"StringFilter"}}},{"kind":"InputValueDefinition","name":{"kind":"Name","value":"isExternal"},"type":{"kind":"NamedType","name":{"kind":"Name","value":"BooleanFilter"}}},{"kind":"InputValueDefinition","name":{"kind":"Name","value":"category"},"type":{"kind":"NamedType","name":{"kind":"Name","value":"ResourceLinkCategoryFilter"}}}]},{"kind":"InputObjectTypeDefinition","name":{"kind":"Name","value":"ResourceArticleContentYoutubeFilter"},"fields":[{"kind":"InputValueDefinition","name":{"kind":"Name","value":"videoId"},"type":{"kind":"NamedType","name":{"kind":"Name","value":"StringFilter"}}}]},{"kind":"InputObjectTypeDefinition","name":{"kind":"Name","value":"ResourceArticleContentLinkButtonFilter"},"fields":[{"kind":"InputValueDefinition","name":{"kind":"Name","value":"link"},"type":{"kind":"NamedType","name":{"kind":"Name","value":"StringFilter"}}},{"kind":"InputValueDefinition","name":{"kind":"Name","value":"label"},"type":{"kind":"NamedType","name":{"kind":"Name","value":"StringFilter"}}}]},{"kind":"InputObjectTypeDefinition","name":{"kind":"Name","value":"ResourceArticleContentFilter"},"fields":[{"kind":"InputValueDefinition","name":{"kind":"Name","value":"Youtube"},"type":{"kind":"NamedType","name":{"kind":"Name","value":"ResourceArticleContentYoutubeFilter"}}},{"kind":"InputValueDefinition","name":{"kind":"Name","value":"LinkButton"},"type":{"kind":"NamedType","name":{"kind":"Name","value":"ResourceArticleContentLinkButtonFilter"}}}]},{"kind":"InputObjectTypeDefinition","name":{"kind":"Name","value":"ResourceArticleCategoryFilter"},"fields":[{"kind":"InputValueDefinition","name":{"kind":"Name","value":"category"},"type":{"kind":"NamedType","name":{"kind":"Name","value":"CategoryFilter"}}}]},{"kind":"InputObjectTypeDefinition","name":{"kind":"Name","value":"ResourceArticleFilter"},"fields":[{"kind":"InputValueDefinition","name":{"kind":"Name","value":"title"},"type":{"kind":"NamedType","name":{"kind":"Name","value":"StringFilter"}}},{"kind":"InputValueDefinition","name":{"kind":"Name","value":"slug"},"type":{"kind":"NamedType","name":{"kind":"Name","value":"StringFilter"}}},{"kind":"InputValueDefinition","name":{"kind":"Name","value":"content"},"type":{"kind":"NamedType","name":{"kind":"Name","value":"ResourceArticleContentFilter"}}},{"kind":"InputValueDefinition","name":{"kind":"Name","value":"category"},"type":{"kind":"NamedType","name":{"kind":"Name","value":"ResourceArticleCategoryFilter"}}}]},{"kind":"InputObjectTypeDefinition","name":{"kind":"Name","value":"ResourceFilter"},"fields":[{"kind":"InputValueDefinition","name":{"kind":"Name","value":"link"},"type":{"kind":"NamedType","name":{"kind":"Name","value":"ResourceLinkFilter"}}},{"kind":"InputValueDefinition","name":{"kind":"Name","value":"article"},"type":{"kind":"NamedType","name":{"kind":"Name","value":"ResourceArticleFilter"}}}]},{"kind":"ObjectTypeDefinition","interfaces":[],"directives":[],"name":{"kind":"Name","value":"ResourceConnectionEdges"},"fields":[{"kind":"FieldDefinition","name":{"kind":"Name","value":"cursor"},"arguments":[],"type":{"kind":"NonNullType","type":{"kind":"NamedType","name":{"kind":"Name","value":"String"}}}},{"kind":"FieldDefinition","name":{"kind":"Name","value":"node"},"arguments":[],"type":{"kind":"NamedType","name":{"kind":"Name","value":"Resource"}}}]},{"kind":"ObjectTypeDefinition","interfaces":[{"kind":"NamedType","name":{"kind":"Name","value":"Connection"}}],"directives":[],"name":{"kind":"Name","value":"ResourceConnection"},"fields":[{"kind":"FieldDefinition","name":{"kind":"Name","value":"pageInfo"},"arguments":[],"type":{"kind":"NonNullType","type":{"kind":"NamedType","name":{"kind":"Name","value":"PageInfo"}}}},{"kind":"FieldDefinition","name":{"kind":"Name","value":"totalCount"},"arguments":[],"type":{"kind":"NonNullType","type":{"kind":"NamedType","name":{"kind":"Name","value":"Float"}}}},{"kind":"FieldDefinition","name":{"kind":"Name","value":"edges"},"arguments":[],"type":{"kind":"ListType","type":{"kind":"NamedType","name":{"kind":"Name","value":"ResourceConnectionEdges"}}}}]},{"kind":"ObjectTypeDefinition","interfaces":[{"kind":"NamedType","name":{"kind":"Name","value":"Node"}},{"kind":"NamedType","name":{"kind":"Name","value":"Document"}}],"directives":[],"name":{"kind":"Name","value":"Timeline"},"fields":[{"kind":"FieldDefinition","name":{"kind":"Name","value":"timestamp"},"arguments":[],"type":{"kind":"NonNullType","type":{"kind":"NamedType","name":{"kind":"Name","value":"String"}}}},{"kind":"FieldDefinition","name":{"kind":"Name","value":"title"},"arguments":[],"type":{"kind":"NonNullType","type":{"kind":"NamedType","name":{"kind":"Name","value":"String"}}}},{"kind":"FieldDefinition","name":{"kind":"Name","value":"content"},"arguments":[],"type":{"kind":"NamedType","name":{"kind":"Name","value":"JSON"}}},{"kind":"FieldDefinition","name":{"kind":"Name","value":"id"},"arguments":[],"type":{"kind":"NonNullType","type":{"kind":"NamedType","name":{"kind":"Name","value":"ID"}}}},{"kind":"FieldDefinition","name":{"kind":"Name","value":"_sys"},"arguments":[],"type":{"kind":"NonNullType","type":{"kind":"NamedType","name":{"kind":"Name","value":"SystemInfo"}}}},{"kind":"FieldDefinition","name":{"kind":"Name","value":"_values"},"arguments":[],"type":{"kind":"NonNullType","type":{"kind":"NamedType","name":{"kind":"Name","value":"JSON"}}}}]},{"kind":"InputObjectTypeDefinition","name":{"kind":"Name","value":"DatetimeFilter"},"fields":[{"kind":"InputValueDefinition","name":{"kind":"Name","value":"after"},"type":{"kind":"NamedType","name":{"kind":"Name","value":"String"}}},{"kind":"InputValueDefinition","name":{"kind":"Name","value":"before"},"type":{"kind":"NamedType","name":{"kind":"Name","value":"String"}}},{"kind":"InputValueDefinition","name":{"kind":"Name","value":"eq"},"type":{"kind":"NamedType","name":{"kind":"Name","value":"String"}}},{"kind":"InputValueDefinition","name":{"kind":"Name","value":"exists"},"type":{"kind":"NamedType","name":{"kind":"Name","value":"Boolean"}}},{"kind":"InputValueDefinition","name":{"kind":"Name","value":"in"},"type":{"kind":"ListType","type":{"kind":"NamedType","name":{"kind":"Name","value":"String"}}}}]},{"kind":"InputObjectTypeDefinition","name":{"kind":"Name","value":"TimelineContentYoutubeFilter"},"fields":[{"kind":"InputValueDefinition","name":{"kind":"Name","value":"videoId"},"type":{"kind":"NamedType","name":{"kind":"Name","value":"StringFilter"}}}]},{"kind":"InputObjectTypeDefinition","name":{"kind":"Name","value":"TimelineContentLinkButtonFilter"},"fields":[{"kind":"InputValueDefinition","name":{"kind":"Name","value":"link"},"type":{"kind":"NamedType","name":{"kind":"Name","value":"StringFilter"}}},{"kind":"InputValueDefinition","name":{"kind":"Name","value":"label"},"type":{"kind":"NamedType","name":{"kind":"Name","value":"StringFilter"}}}]},{"kind":"InputObjectTypeDefinition","name":{"kind":"Name","value":"TimelineContentFilter"},"fields":[{"kind":"InputValueDefinition","name":{"kind":"Name","value":"Youtube"},"type":{"kind":"NamedType","name":{"kind":"Name","value":"TimelineContentYoutubeFilter"}}},{"kind":"InputValueDefinition","name":{"kind":"Name","value":"LinkButton"},"type":{"kind":"NamedType","name":{"kind":"Name","value":"TimelineContentLinkButtonFilter"}}}]},{"kind":"InputObjectTypeDefinition","name":{"kind":"Name","value":"TimelineFilter"},"fields":[{"kind":"InputValueDefinition","name":{"kind":"Name","value":"timestamp"},"type":{"kind":"NamedType","name":{"kind":"Name","value":"DatetimeFilter"}}},{"kind":"InputValueDefinition","name":{"kind":"Name","value":"title"},"type":{"kind":"NamedType","name":{"kind":"Name","value":"StringFilter"}}},{"kind":"InputValueDefinition","name":{"kind":"Name","value":"content"},"type":{"kind":"NamedType","name":{"kind":"Name","value":"TimelineContentFilter"}}}]},{"kind":"ObjectTypeDefinition","interfaces":[],"directives":[],"name":{"kind":"Name","value":"TimelineConnectionEdges"},"fields":[{"kind":"FieldDefinition","name":{"kind":"Name","value":"cursor"},"arguments":[],"type":{"kind":"NonNullType","type":{"kind":"NamedType","name":{"kind":"Name","value":"String"}}}},{"kind":"FieldDefinition","name":{"kind":"Name","value":"node"},"arguments":[],"type":{"kind":"NamedType","name":{"kind":"Name","value":"Timeline"}}}]},{"kind":"ObjectTypeDefinition","interfaces":[{"kind":"NamedType","name":{"kind":"Name","value":"Connection"}}],"directives":[],"name":{"kind":"Name","value":"TimelineConnection"},"fields":[{"kind":"FieldDefinition","name":{"kind":"Name","value":"pageInfo"},"arguments":[],"type":{"kind":"NonNullType","type":{"kind":"NamedType","name":{"kind":"Name","value":"PageInfo"}}}},{"kind":"FieldDefinition","name":{"kind":"Name","value":"totalCount"},"arguments":[],"type":{"kind":"NonNullType","type":{"kind":"NamedType","name":{"kind":"Name","value":"Float"}}}},{"kind":"FieldDefinition","name":{"kind":"Name","value":"edges"},"arguments":[],"type":{"kind":"ListType","type":{"kind":"NamedType","name":{"kind":"Name","value":"TimelineConnectionEdges"}}}}]},{"kind":"ObjectTypeDefinition","interfaces":[],"directives":[],"name":{"kind":"Name","value":"Mutation"},"fields":[{"kind":"FieldDefinition","name":{"kind":"Name","value":"addPendingDocument"},"arguments":[{"kind":"InputValueDefinition","name":{"kind":"Name","value":"collection"},"type":{"kind":"NonNullType","type":{"kind":"NamedType","name":{"kind":"Name","value":"String"}}}},{"kind":"InputValueDefinition","name":{"kind":"Name","value":"relativePath"},"type":{"kind":"NonNullType","type":{"kind":"NamedType","name":{"kind":"Name","value":"String"}}}},{"kind":"InputValueDefinition","name":{"kind":"Name","value":"template"},"type":{"kind":"NamedType","name":{"kind":"Name","value":"String"}}}],"type":{"kind":"NonNullType","type":{"kind":"NamedType","name":{"kind":"Name","value":"DocumentNode"}}}},{"kind":"FieldDefinition","name":{"kind":"Name","value":"updateDocument"},"arguments":[{"kind":"InputValueDefinition","name":{"kind":"Name","value":"collection"},"type":{"kind":"NamedType","name":{"kind":"Name","value":"String"}}},{"kind":"InputValueDefinition","name":{"kind":"Name","value":"relativePath"},"type":{"kind":"NonNullType","type":{"kind":"NamedType","name":{"kind":"Name","value":"String"}}}},{"kind":"InputValueDefinition","name":{"kind":"Name","value":"params"},"type":{"kind":"NonNullType","type":{"kind":"NamedType","name":{"kind":"Name","value":"DocumentUpdateMutation"}}}}],"type":{"kind":"NonNullType","type":{"kind":"NamedType","name":{"kind":"Name","value":"DocumentNode"}}}},{"kind":"FieldDefinition","name":{"kind":"Name","value":"deleteDocument"},"arguments":[{"kind":"InputValueDefinition","name":{"kind":"Name","value":"collection"},"type":{"kind":"NamedType","name":{"kind":"Name","value":"String"}}},{"kind":"InputValueDefinition","name":{"kind":"Name","value":"relativePath"},"type":{"kind":"NonNullType","type":{"kind":"NamedType","name":{"kind":"Name","value":"String"}}}}],"type":{"kind":"NonNullType","type":{"kind":"NamedType","name":{"kind":"Name","value":"DocumentNode"}}}},{"kind":"FieldDefinition","name":{"kind":"Name","value":"createDocument"},"arguments":[{"kind":"InputValueDefinition","name":{"kind":"Name","value":"collection"},"type":{"kind":"NamedType","name":{"kind":"Name","value":"String"}}},{"kind":"InputValueDefinition","name":{"kind":"Name","value":"relativePath"},"type":{"kind":"NonNullType","type":{"kind":"NamedType","name":{"kind":"Name","value":"String"}}}},{"kind":"InputValueDefinition","name":{"kind":"Name","value":"params"},"type":{"kind":"NonNullType","type":{"kind":"NamedType","name":{"kind":"Name","value":"DocumentMutation"}}}}],"type":{"kind":"NonNullType","type":{"kind":"NamedType","name":{"kind":"Name","value":"DocumentNode"}}}},{"kind":"FieldDefinition","name":{"kind":"Name","value":"createFolder"},"arguments":[{"kind":"InputValueDefinition","name":{"kind":"Name","value":"collection"},"type":{"kind":"NamedType","name":{"kind":"Name","value":"String"}}},{"kind":"InputValueDefinition","name":{"kind":"Name","value":"relativePath"},"type":{"kind":"NonNullType","type":{"kind":"NamedType","name":{"kind":"Name","value":"String"}}}}],"type":{"kind":"NonNullType","type":{"kind":"NamedType","name":{"kind":"Name","value":"DocumentNode"}}}},{"kind":"FieldDefinition","name":{"kind":"Name","value":"updateCategory"},"arguments":[{"kind":"InputValueDefinition","name":{"kind":"Name","value":"relativePath"},"type":{"kind":"NonNullType","type":{"kind":"NamedType","name":{"kind":"Name","value":"String"}}}},{"kind":"InputValueDefinition","name":{"kind":"Name","value":"params"},"type":{"kind":"NonNullType","type":{"kind":"NamedType","name":{"kind":"Name","value":"CategoryMutation"}}}}],"type":{"kind":"NonNullType","type":{"kind":"NamedType","name":{"kind":"Name","value":"Category"}}}},{"kind":"FieldDefinition","name":{"kind":"Name","value":"createCategory"},"arguments":[{"kind":"InputValueDefinition","name":{"kind":"Name","value":"relativePath"},"type":{"kind":"NonNullType","type":{"kind":"NamedType","name":{"kind":"Name","value":"String"}}}},{"kind":"InputValueDefinition","name":{"kind":"Name","value":"params"},"type":{"kind":"NonNullType","type":{"kind":"NamedType","name":{"kind":"Name","value":"CategoryMutation"}}}}],"type":{"kind":"NonNullType","type":{"kind":"NamedType","name":{"kind":"Name","value":"Category"}}}},{"kind":"FieldDefinition","name":{"kind":"Name","value":"updateResource"},"arguments":[{"kind":"InputValueDefinition","name":{"kind":"Name","value":"relativePath"},"type":{"kind":"NonNullType","type":{"kind":"NamedType","name":{"kind":"Name","value":"String"}}}},{"kind":"InputValueDefinition","name":{"kind":"Name","value":"params"},"type":{"kind":"NonNullType","type":{"kind":"NamedType","name":{"kind":"Name","value":"ResourceMutation"}}}}],"type":{"kind":"NonNullType","type":{"kind":"NamedType","name":{"kind":"Name","value":"Resource"}}}},{"kind":"FieldDefinition","name":{"kind":"Name","value":"createResource"},"arguments":[{"kind":"InputValueDefinition","name":{"kind":"Name","value":"relativePath"},"type":{"kind":"NonNullType","type":{"kind":"NamedType","name":{"kind":"Name","value":"String"}}}},{"kind":"InputValueDefinition","name":{"kind":"Name","value":"params"},"type":{"kind":"NonNullType","type":{"kind":"NamedType","name":{"kind":"Name","value":"ResourceMutation"}}}}],"type":{"kind":"NonNullType","type":{"kind":"NamedType","name":{"kind":"Name","value":"Resource"}}}},{"kind":"FieldDefinition","name":{"kind":"Name","value":"updateTimeline"},"arguments":[{"kind":"InputValueDefinition","name":{"kind":"Name","value":"relativePath"},"type":{"kind":"NonNullType","type":{"kind":"NamedType","name":{"kind":"Name","value":"String"}}}},{"kind":"InputValueDefinition","name":{"kind":"Name","value":"params"},"type":{"kind":"NonNullType","type":{"kind":"NamedType","name":{"kind":"Name","value":"TimelineMutation"}}}}],"type":{"kind":"NonNullType","type":{"kind":"NamedType","name":{"kind":"Name","value":"Timeline"}}}},{"kind":"FieldDefinition","name":{"kind":"Name","value":"createTimeline"},"arguments":[{"kind":"InputValueDefinition","name":{"kind":"Name","value":"relativePath"},"type":{"kind":"NonNullType","type":{"kind":"NamedType","name":{"kind":"Name","value":"String"}}}},{"kind":"InputValueDefinition","name":{"kind":"Name","value":"params"},"type":{"kind":"NonNullType","type":{"kind":"NamedType","name":{"kind":"Name","value":"TimelineMutation"}}}}],"type":{"kind":"NonNullType","type":{"kind":"NamedType","name":{"kind":"Name","value":"Timeline"}}}}]},{"kind":"InputObjectTypeDefinition","name":{"kind":"Name","value":"DocumentUpdateMutation"},"fields":[{"kind":"InputValueDefinition","name":{"kind":"Name","value":"category"},"type":{"kind":"NamedType","name":{"kind":"Name","value":"CategoryMutation"}}},{"kind":"InputValueDefinition","name":{"kind":"Name","value":"resource"},"type":{"kind":"NamedType","name":{"kind":"Name","value":"ResourceMutation"}}},{"kind":"InputValueDefinition","name":{"kind":"Name","value":"timeline"},"type":{"kind":"NamedType","name":{"kind":"Name","value":"TimelineMutation"}}},{"kind":"InputValueDefinition","name":{"kind":"Name","value":"relativePath"},"type":{"kind":"NamedType","name":{"kind":"Name","value":"String"}}}]},{"kind":"InputObjectTypeDefinition","name":{"kind":"Name","value":"DocumentMutation"},"fields":[{"kind":"InputValueDefinition","name":{"kind":"Name","value":"category"},"type":{"kind":"NamedType","name":{"kind":"Name","value":"CategoryMutation"}}},{"kind":"InputValueDefinition","name":{"kind":"Name","value":"resource"},"type":{"kind":"NamedType","name":{"kind":"Name","value":"ResourceMutation"}}},{"kind":"InputValueDefinition","name":{"kind":"Name","value":"timeline"},"type":{"kind":"NamedType","name":{"kind":"Name","value":"TimelineMutation"}}}]},{"kind":"InputObjectTypeDefinition","name":{"kind":"Name","value":"CategoryMutation"},"fields":[{"kind":"InputValueDefinition","name":{"kind":"Name","value":"precedence"},"type":{"kind":"NamedType","name":{"kind":"Name","value":"Float"}}},{"kind":"InputValueDefinition","name":{"kind":"Name","value":"label"},"type":{"kind":"NamedType","name":{"kind":"Name","value":"String"}}},{"kind":"InputValueDefinition","name":{"kind":"Name","value":"title"},"type":{"kind":"NamedType","name":{"kind":"Name","value":"String"}}},{"kind":"InputValueDefinition","name":{"kind":"Name","value":"description"},"type":{"kind":"NamedType","name":{"kind":"Name","value":"String"}}}]},{"kind":"InputObjectTypeDefinition","name":{"kind":"Name","value":"ResourceLinkMutation"},"fields":[{"kind":"InputValueDefinition","name":{"kind":"Name","value":"title"},"type":{"kind":"NamedType","name":{"kind":"Name","value":"String"}}},{"kind":"InputValueDefinition","name":{"kind":"Name","value":"link"},"type":{"kind":"NamedType","name":{"kind":"Name","value":"String"}}},{"kind":"InputValueDefinition","name":{"kind":"Name","value":"isExternal"},"type":{"kind":"NamedType","name":{"kind":"Name","value":"Boolean"}}},{"kind":"InputValueDefinition","name":{"kind":"Name","value":"category"},"type":{"kind":"NamedType","name":{"kind":"Name","value":"String"}}}]},{"kind":"InputObjectTypeDefinition","name":{"kind":"Name","value":"ResourceArticleMutation"},"fields":[{"kind":"InputValueDefinition","name":{"kind":"Name","value":"title"},"type":{"kind":"NamedType","name":{"kind":"Name","value":"String"}}},{"kind":"InputValueDefinition","name":{"kind":"Name","value":"slug"},"type":{"kind":"NamedType","name":{"kind":"Name","value":"String"}}},{"kind":"InputValueDefinition","name":{"kind":"Name","value":"content"},"type":{"kind":"NamedType","name":{"kind":"Name","value":"JSON"}}},{"kind":"InputValueDefinition","name":{"kind":"Name","value":"category"},"type":{"kind":"NamedType","name":{"kind":"Name","value":"String"}}}]},{"kind":"InputObjectTypeDefinition","name":{"kind":"Name","value":"ResourceMutation"},"fields":[{"kind":"InputValueDefinition","name":{"kind":"Name","value":"link"},"type":{"kind":"NamedType","name":{"kind":"Name","value":"ResourceLinkMutation"}}},{"kind":"InputValueDefinition","name":{"kind":"Name","value":"article"},"type":{"kind":"NamedType","name":{"kind":"Name","value":"ResourceArticleMutation"}}}]},{"kind":"InputObjectTypeDefinition","name":{"kind":"Name","value":"TimelineMutation"},"fields":[{"kind":"InputValueDefinition","name":{"kind":"Name","value":"timestamp"},"type":{"kind":"NamedType","name":{"kind":"Name","value":"String"}}},{"kind":"InputValueDefinition","name":{"kind":"Name","value":"title"},"type":{"kind":"NamedType","name":{"kind":"Name","value":"String"}}},{"kind":"InputValueDefinition","name":{"kind":"Name","value":"content"},"type":{"kind":"NamedType","name":{"kind":"Name","value":"JSON"}}}]}]}}